obelix/__init__.py
obelix/utils.py
obelix_data-1.2.0.dist-info/METADATA
obelix_data-1.2.0.dist-info/WHEEL
obelix_data-1.2.0.dist-info/licenses/LICENSE.txt
obelix_data-1.2.0.dist-info/RECORD
