Metadata-Version: 2.4
Name: obelix-data
Version: 1.2.0
Summary: A Curated Dataset of Crystal Structures and Experimentally Measured Ionic Conductivities for Lithium Solid-State Electrolytes
Project-URL: Repository, https://github.com/NRC-Mila/OBELiX
Maintainer-email: Felix Therrien <felix.therrien@gmail.com>
License-Expression: MIT
License-File: LICENSE.txt
Keywords: batteries,database,dataset,ionic-conductivity,solid-state
Requires-Python: >=3.8
Requires-Dist: pandas
Requires-Dist: pymatgen
Requires-Dist: tqdm
